{
  "manufacturer": "Ayrton",
  "fixtures": [
    {
      "fixture": "Bora",
      "watts": 1150,
      "weight": 37.8,
      "modes": {
        "Basic": 30,
        "Standard": 32,
        "Extended": 52
      },
      "gdtf": {
        "status": "matched",
        "folder": "fixtures/ayrton",
        "suggestedFileName": "Ayrton__Bora.gdtf",
        "file": "fixtures/ayrton/Ayrton@Bora@V2.3_Add_RDM_Personality.gdtf",
        "modes": {
          "Basic": {
            "channels": 30,
            "gdtfMode": "Basic_540",
            "status": "matched"
          },
          "Standard": {
            "channels": 32,
            "gdtfMode": "Standard_540",
            "status": "matched"
          },
          "Extended": {
            "channels": 52,
            "gdtfMode": "Extended_540",
            "status": "matched"
          }
        }
      },
      "shortName": "Bora"
    },
    {
      "fixture": "Cobra",
      "watts": 480,
      "weight": 33,
      "modes": {
        "Basic": 33,
        "Standard": 36,
        "Extended": 45
      },
      "gdtf": {
        "status": "pending-match",
        "folder": "fixtures/ayrton",
        "suggestedFileName": "Ayrton__Cobra.gdtf",
        "file": "fixtures/ayrton/Ayrton@Cobra@V1.7_Add_RDM_Personality.gdtf",
        "modes": {
          "Basic": {
            "channels": 33,
            "gdtfMode": "",
            "status": "pending-match"
          },
          "Standard": {
            "channels": 36,
            "gdtfMode": "",
            "status": "pending-match"
          },
          "Extended": {
            "channels": 45,
            "gdtfMode": "Extended_540",
            "status": "matched"
          }
        }
      },
      "shortName": "Cobra"
    },
    {
      "fixture": "Diablo Profile S",
      "watts": 550,
      "weight": 22,
      "modes": {
        "Basic": 34,
        "Standard": 36,
        "Extended": 56
      },
      "gdtf": {
        "status": "matched",
        "folder": "fixtures/ayrton",
        "suggestedFileName": "Ayrton__Diablo_Profile_S.gdtf",
        "file": "fixtures/ayrton/Ayrton@Diablo@V2.6_Add_RDM_Personality.gdtf",
        "modes": {
          "Basic": {
            "channels": 34,
            "gdtfMode": "Basic_540_S",
            "status": "matched"
          },
          "Standard": {
            "channels": 36,
            "gdtfMode": "Standard_540_S",
            "status": "matched"
          },
          "Extended": {
            "channels": 56,
            "gdtfMode": "Extended_540_S",
            "status": "matched"
          }
        }
      },
      "shortName": "Diablo Prof S"
    },
    {
      "fixture": "Domino LT",
      "watts": 1600,
      "weight": 60,
      "modes": {
        "Standard": 46,
        "Extended": 70
      },
      "gdtf": {
        "status": "matched",
        "folder": "fixtures/ayrton",
        "suggestedFileName": "Ayrton__Domino_LT.gdtf",
        "file": "fixtures/ayrton/Ayrton@Domino_LT@V1.8_Add_RDM_Personality.gdtf",
        "modes": {
          "Standard": {
            "channels": 46,
            "gdtfMode": "Standard_540",
            "status": "matched"
          },
          "Extended": {
            "channels": 70,
            "gdtfMode": "Extended_540",
            "status": "matched"
          }
        }
      },
      "shortName": "Domino LT"
    },
    {
      "fixture": "Domino Profile",
      "watts": 1800,
      "weight": 52,
      "modes": {
        "Basic": 42,
        "Standard": 44,
        "Extended": 66
      },
      "gdtf": {
        "status": "matched",
        "folder": "fixtures/ayrton",
        "suggestedFileName": "Ayrton__Domino_Profile.gdtf",
        "file": "fixtures/ayrton/Ayrton@Domino_Profile@V2.6_Add_RDM_Personality.gdtf",
        "modes": {
          "Basic": {
            "channels": 42,
            "gdtfMode": "Basic_540",
            "status": "matched"
          },
          "Standard": {
            "channels": 44,
            "gdtfMode": "Standard_540",
            "status": "matched"
          },
          "Extended": {
            "channels": 66,
            "gdtfMode": "Extended_540",
            "status": "matched"
          }
        }
      },
      "shortName": "Domino Prof"
    },
    {
      "fixture": "Domino Wash",
      "watts": 1600,
      "weight": 52,
      "modes": {
        "Basic": 37,
        "Standard": 39,
        "Extended": 61
      },
      "gdtf": {
        "status": "matched",
        "folder": "fixtures/ayrton",
        "suggestedFileName": "Ayrton__Domino_Wash.gdtf",
        "file": "fixtures/ayrton/Ayrton@Domino_Wash@V1.4_Add_RDM_Personality.gdtf",
        "modes": {
          "Basic": {
            "channels": 37,
            "gdtfMode": "Basic_540",
            "status": "matched"
          },
          "Standard": {
            "channels": 39,
            "gdtfMode": "Standard_540",
            "status": "matched"
          },
          "Extended": {
            "channels": 61,
            "gdtfMode": "Extended_540",
            "status": "matched"
          }
        }
      },
      "shortName": "Domino Wsh"
    },
    {
      "fixture": "Eagle Strike",
      "watts": 1295,
      "weight": 54.7,
      "modes": {
        "Standard": 44,
        "Extended": 66
      },
      "gdtf": {
        "status": "matched",
        "folder": "fixtures/ayrton",
        "suggestedFileName": "Ayrton__Eagle_Strike.gdtf",
        "file": "fixtures/ayrton/Ayrton@EagleStrike@V1.3_Add_RDM_Personality.gdtf",
        "modes": {
          "Standard": {
            "channels": 44,
            "gdtfMode": "Standard_540",
            "status": "matched"
          },
          "Extended": {
            "channels": 66,
            "gdtfMode": "Extended_540",
            "status": "matched"
          }
        }
      },
      "shortName": "Eagle Strike"
    },
    {
      "fixture": "Eurus",
      "watts": 1000,
      "weight": 33,
      "modes": {
        "Basic": 39,
        "Standard": 41,
        "Extended": 62
      },
      "gdtf": {
        "status": "matched",
        "folder": "fixtures/ayrton",
        "suggestedFileName": "Ayrton__Eurus.gdtf",
        "file": "fixtures/ayrton/Ayrton@Eurus@V2.7_Add_RDM_Personality.gdtf",
        "modes": {
          "Basic": {
            "channels": 39,
            "gdtfMode": "Basic_540",
            "status": "matched"
          },
          "Standard": {
            "channels": 41,
            "gdtfMode": "Standard_540",
            "status": "matched"
          },
          "Extended": {
            "channels": 62,
            "gdtfMode": "Extended_540",
            "status": "matched"
          }
        }
      },
      "shortName": "Eurus"
    },
    {
      "fixture": "Ghibli",
      "watts": 800,
      "weight": 35.6,
      "modes": {
        "Basic": 36,
        "Standard": 38,
        "Extended": 58
      },
      "gdtf": {
        "status": "matched",
        "folder": "fixtures/ayrton",
        "suggestedFileName": "Ayrton__Ghibli.gdtf",
        "file": "fixtures/ayrton/Ayrton@Ghibli@V2.4_Add_RDM_Personality.gdtf",
        "modes": {
          "Basic": {
            "channels": 36,
            "gdtfMode": "Basic_540",
            "status": "matched"
          },
          "Standard": {
            "channels": 38,
            "gdtfMode": "Standard_540",
            "status": "matched"
          },
          "Extended": {
            "channels": 58,
            "gdtfMode": "Extended_540",
            "status": "matched"
          }
        }
      },
      "shortName": "Ghibli"
    },
    {
      "fixture": "Huracan LT",
      "watts": 1470,
      "weight": 53.8,
      "modes": {
        "Basic": 44,
        "Standard": 46,
        "Extended": 70
      },
      "gdtf": {
        "status": "matched",
        "folder": "fixtures/ayrton",
        "suggestedFileName": "Ayrton__Huracan_LT.gdtf",
        "file": "fixtures/ayrton/Ayrton@Huracan_LT@V1.5_Add_RDM_Personality.gdtf",
        "modes": {
          "Basic": {
            "channels": 44,
            "gdtfMode": "Basic_540",
            "status": "matched"
          },
          "Standard": {
            "channels": 46,
            "gdtfMode": "Standard_540",
            "status": "matched"
          },
          "Extended": {
            "channels": 70,
            "gdtfMode": "Extended_540",
            "status": "matched"
          }
        }
      },
      "shortName": "Huracan LT"
    },
    {
      "fixture": "Huracan Profile",
      "watts": 1470,
      "weight": 46,
      "modes": {
        "Basic": 44,
        "Standard": 46,
        "Extended": 70
      },
      "gdtf": {
        "status": "matched",
        "folder": "fixtures/ayrton",
        "suggestedFileName": "Ayrton__Huracan_Profile.gdtf",
        "file": "fixtures/ayrton/Ayrton@Huracan_Profile@V2.6_Add_RDM_Personality.gdtf",
        "modes": {
          "Basic": {
            "channels": 44,
            "gdtfMode": "Basic_ 540",
            "status": "matched"
          },
          "Standard": {
            "channels": 46,
            "gdtfMode": "Standard_ 540",
            "status": "matched"
          },
          "Extended": {
            "channels": 70,
            "gdtfMode": "Extended_540",
            "status": "matched"
          }
        }
      },
      "shortName": "Huracan Prof"
    },
    {
      "fixture": "Karif LT",
      "watts": 550,
      "weight": 27,
      "modes": {
        "Basic": 32,
        "Standard": 34,
        "Extended": 46
      },
      "gdtf": {
        "status": "pending-download",
        "folder": "fixtures/ayrton",
        "suggestedFileName": "Ayrton__Karif_LT.gdtf",
        "file": "",
        "modes": {
          "Basic": {
            "channels": 32,
            "gdtfMode": "",
            "status": "pending-match"
          },
          "Standard": {
            "channels": 34,
            "gdtfMode": "",
            "status": "pending-match"
          },
          "Extended": {
            "channels": 46,
            "gdtfMode": "",
            "status": "pending-match"
          }
        }
      },
      "shortName": "Karif LT"
    },
    {
      "fixture": "Khamsin",
      "watts": 1550,
      "weight": 39.8,
      "modes": {
        "Basic": 40,
        "Standard": 42,
        "Extended": 64
      },
      "gdtf": {
        "status": "matched",
        "folder": "fixtures/ayrton",
        "suggestedFileName": "Ayrton__Khamsin.gdtf",
        "file": "fixtures/ayrton/Ayrton@Khamsin@V12.3_Add_RDM_Personality.gdtf",
        "modes": {
          "Basic": {
            "channels": 40,
            "gdtfMode": "Basic_540",
            "status": "matched"
          },
          "Standard": {
            "channels": 42,
            "gdtfMode": "Standard_540",
            "status": "matched"
          },
          "Extended": {
            "channels": 64,
            "gdtfMode": "Extended_540",
            "status": "matched"
          }
        }
      },
      "shortName": "Khamsin"
    },
    {
      "fixture": "Kyalami",
      "watts": 200,
      "weight": 14.5,
      "modes": {
        "Standard": 33
      },
      "gdtf": {
        "status": "pending-match",
        "folder": "fixtures/ayrton",
        "suggestedFileName": "Ayrton__Kyalami.gdtf",
        "file": "fixtures/ayrton/Ayrton@Kyalami@V1.7_Add_RDM_Personality.gdtf",
        "modes": {
          "Standard": {
            "channels": 33,
            "gdtfMode": "",
            "status": "pending-match"
          }
        }
      },
      "shortName": "Kyalami"
    },
    {
      "fixture": "Magic Blade Neo",
      "watts": 800,
      "weight": 32.4,
      "modes": {
        "Standard": 175,
        "Extended": 184
      },
      "gdtf": {
        "status": "pending-match",
        "folder": "fixtures/ayrton",
        "suggestedFileName": "Ayrton__Magic_Blade_Neo.gdtf",
        "file": "fixtures/ayrton/Ayrton@MagicBlade_Neo@V1.1_Add_RDM_Personality.gdtf",
        "modes": {
          "Standard": {
            "channels": 175,
            "gdtfMode": "",
            "status": "pending-match"
          },
          "Extended": {
            "channels": 184,
            "gdtfMode": "",
            "status": "pending-match"
          }
        }
      },
      "shortName": "Magic Blade Neo"
    },
    {
      "fixture": "Magic Dot Neo",
      "watts": 160,
      "weight": 6.6,
      "modes": {
        "Standard": 35
      },
      "gdtf": {
        "status": "pending-match",
        "folder": "fixtures/ayrton",
        "suggestedFileName": "Ayrton__Magic_Dot_Neo.gdtf",
        "file": "fixtures/ayrton/Ayrton@MagicDot_Neo@V1.2_Add_RDM_Personality.gdtf",
        "modes": {
          "Standard": {
            "channels": 35,
            "gdtfMode": "",
            "status": "pending-match"
          }
        }
      },
      "shortName": "Magic Dot Neo"
    },
    {
      "fixture": "Mamba",
      "watts": 800,
      "weight": 41,
      "modes": {
        "Extended": 47
      },
      "gdtf": {
        "status": "matched",
        "folder": "fixtures/ayrton",
        "suggestedFileName": "Ayrton__Mamba.gdtf",
        "file": "fixtures/ayrton/Ayrton@Mamba@V1.5_Add_RDM_Personality.gdtf",
        "modes": {
          "Extended": {
            "channels": 47,
            "gdtfMode": "Extended_540",
            "status": "matched"
          }
        }
      },
      "shortName": "Mamba"
    },
    {
      "fixture": "MiniPanel FX",
      "watts": 220,
      "weight": 8.9,
      "modes": {
        "Basic": 19,
        "Standard": 22,
        "Extended": 34
      },
      "gdtf": {
        "status": "pending-match",
        "folder": "fixtures/ayrton",
        "suggestedFileName": "Ayrton__MiniPanel_FX.gdtf",
        "file": "fixtures/ayrton/Ayrton@MiniPanel_FX@V2.5_Add_RDM_Personality.gdtf",
        "modes": {
          "Basic": {
            "channels": 19,
            "gdtfMode": "Basic",
            "status": "matched"
          },
          "Standard": {
            "channels": 22,
            "gdtfMode": "Standard",
            "status": "matched"
          },
          "Extended": {
            "channels": 34,
            "gdtfMode": "",
            "status": "pending-match"
          }
        }
      },
      "shortName": "MiniPanel FX"
    },
    {
      "fixture": "Mistral",
      "watts": 550,
      "weight": 18.6,
      "modes": {
        "Standard": 39
      },
      "gdtf": {
        "status": "pending-match",
        "folder": "fixtures/ayrton",
        "suggestedFileName": "Ayrton__Mistral.gdtf",
        "file": "fixtures/ayrton/Ayrton@Mistral@V2.3_Add_RDM_Personality.gdtf",
        "modes": {
          "Standard": {
            "channels": 39,
            "gdtfMode": "",
            "status": "pending-match"
          }
        }
      },
      "shortName": "Mistral"
    },
    {
      "fixture": "Perseo Profile",
      "watts": 1480,
      "weight": 38.8,
      "modes": {
        "Basic": 38,
        "Standard": 40,
        "Extended": 61
      },
      "gdtf": {
        "status": "matched",
        "folder": "fixtures/ayrton",
        "suggestedFileName": "Ayrton__Perseo_Profile.gdtf",
        "file": "fixtures/ayrton/Ayrton@Perseo_Profile@V2.3_Add_RDM_Personality.gdtf",
        "modes": {
          "Basic": {
            "channels": 38,
            "gdtfMode": "Basic_540",
            "status": "matched"
          },
          "Standard": {
            "channels": 40,
            "gdtfMode": "Standard_540",
            "status": "matched"
          },
          "Extended": {
            "channels": 61,
            "gdtfMode": "Extended_540",
            "status": "matched"
          }
        }
      },
      "shortName": "Perseo Prof"
    },
    {
      "fixture": "RawBeam 350",
      "watts": 660,
      "weight": 25.4,
      "modes": {
        "Extended": 43
      },
      "gdtf": {
        "status": "pending-match",
        "folder": "fixtures/ayrton",
        "suggestedFileName": "Ayrton__RawBeam_350.gdtf",
        "file": "fixtures/ayrton/Ayrton@RawBeam_350@V1.3_Add_RDM_Personality.gdtf",
        "modes": {
          "Extended": {
            "channels": 43,
            "gdtfMode": "",
            "status": "pending-match"
          }
        }
      },
      "shortName": "RawBeam 350"
    },
    {
      "fixture": "Rivale Profile",
      "watts": 700,
      "weight": 30.8,
      "modes": {
        "Standard": 42,
        "Extended": 65
      },
      "gdtf": {
        "status": "matched",
        "folder": "fixtures/ayrton",
        "suggestedFileName": "Ayrton__Rivale_Profile.gdtf",
        "file": "fixtures/ayrton/Ayrton@Rivale_Profile@V1.7_Add_RDM_Personality.gdtf",
        "modes": {
          "Standard": {
            "channels": 42,
            "gdtfMode": "Standard_540",
            "status": "matched"
          },
          "Extended": {
            "channels": 65,
            "gdtfMode": "Extended_540",
            "status": "matched"
          }
        }
      },
      "shortName": "Rivale Prof"
    },
    {
      "fixture": "Rivale Wash",
      "watts": 700,
      "weight": 30.8,
      "modes": {
        "Standard": 42,
        "Extended": 60
      },
      "gdtf": {
        "status": "pending-match",
        "folder": "fixtures/ayrton",
        "suggestedFileName": "Ayrton__Rivale_Wash.gdtf",
        "file": "fixtures/ayrton/Ayrton@Rivale_Wash@V1.7_Add_RDM_Personality.gdtf",
        "modes": {
          "Standard": {
            "channels": 42,
            "gdtfMode": "",
            "status": "pending-match"
          },
          "Extended": {
            "channels": 60,
            "gdtfMode": "Extended_540",
            "status": "matched"
          }
        }
      },
      "shortName": "Rivale Wsh"
    },
    {
      "fixture": "Stradale Profile",
      "watts": 630,
      "weight": 23.5,
      "modes": {
        "Standard": 42,
        "Extended": 65
      },
      "gdtf": {
        "status": "matched",
        "folder": "fixtures/ayrton",
        "suggestedFileName": "Ayrton__Stradale_Profile.gdtf",
        "file": "fixtures/ayrton/Ayrton@Stradale_Profile@V1.2_Add_RDM_Personality.gdtf",
        "modes": {
          "Standard": {
            "channels": 42,
            "gdtfMode": "Standard_540",
            "status": "matched"
          },
          "Extended": {
            "channels": 65,
            "gdtfMode": "Extended_540",
            "status": "matched"
          }
        }
      },
      "shortName": "Stradale Prof"
    },
    {
      "fixture": "Veloce Profile",
      "watts": 1300,
      "weight": 40.5,
      "modes": {
        "Standard": 44,
        "Extended": 67
      },
      "gdtf": {
        "status": "matched",
        "folder": "fixtures/ayrton",
        "suggestedFileName": "Ayrton__Veloce_Profile.gdtf",
        "file": "fixtures/ayrton/Ayrton@Veloce_Profile@V1.5_Add_RDM_Personality.gdtf",
        "modes": {
          "Standard": {
            "channels": 44,
            "gdtfMode": "Standard_540",
            "status": "matched"
          },
          "Extended": {
            "channels": 67,
            "gdtfMode": "Extended_540",
            "status": "matched"
          }
        }
      },
      "shortName": "Veloce Prof"
    },
    {
      "fixture": "Veloce Wash",
      "watts": 1300,
      "weight": 39,
      "modes": {
        "Standard": 38,
        "Extended": 60
      },
      "gdtf": {
        "status": "matched",
        "folder": "fixtures/ayrton",
        "suggestedFileName": "Ayrton__Veloce_Wash.gdtf",
        "file": "fixtures/ayrton/Ayrton@Veloce_Wash@V1.2_Add_RDM_Personality.gdtf",
        "modes": {
          "Standard": {
            "channels": 38,
            "gdtfMode": "Standard_540",
            "status": "matched"
          },
          "Extended": {
            "channels": 60,
            "gdtfMode": "Extended_540",
            "status": "matched"
          }
        }
      },
      "shortName": "Veloce Wsh"
    },
    {
      "fixture": "Zonda 3 FX",
      "watts": 400,
      "weight": 11.1,
      "modes": {
        "Basic": 26,
        "Standard": 50,
        "Extended": 79
      },
      "gdtf": {
        "status": "pending-match",
        "folder": "fixtures/ayrton",
        "suggestedFileName": "Ayrton__Zonda_3_FX.gdtf",
        "file": "fixtures/ayrton/Ayrton@Zonda_3_FX@V1.7_Add_RDM_Personality.gdtf",
        "modes": {
          "Basic": {
            "channels": 26,
            "gdtfMode": "Basic",
            "status": "matched"
          },
          "Standard": {
            "channels": 50,
            "gdtfMode": "Standard",
            "status": "matched"
          },
          "Extended": {
            "channels": 79,
            "gdtfMode": "",
            "status": "pending-match"
          }
        }
      },
      "shortName": "Zonda 3 FX"
    },
    {
      "fixture": "Zonda 3 Wash",
      "watts": 400,
      "weight": 11.1,
      "modes": {
        "Basic": 26,
        "Standard": 30,
        "Extended Ring": 46,
        "Extended Pixel": 79
      },
      "gdtf": {
        "status": "pending-match",
        "folder": "fixtures/ayrton",
        "suggestedFileName": "Ayrton__Zonda_3_Wash.gdtf",
        "file": "fixtures/ayrton/Ayrton@Zonda_3_WASH@V1.7_Add_RDM_Personality.gdtf",
        "modes": {
          "Basic": {
            "channels": 26,
            "gdtfMode": "Basic",
            "status": "matched"
          },
          "Standard": {
            "channels": 30,
            "gdtfMode": "",
            "status": "pending-match"
          },
          "Extended Ring": {
            "channels": 46,
            "gdtfMode": "Extended Ring",
            "status": "matched"
          },
          "Extended Pixel": {
            "channels": 79,
            "gdtfMode": "",
            "status": "pending-match"
          }
        }
      },
      "shortName": "Zonda 3 Wsh"
    },
    {
      "fixture": "Zonda 9 FX",
      "watts": 1400,
      "weight": 29.2,
      "modes": {
        "Basic": 26,
        "Standard": 51,
        "Extended Ring": 54,
        "Extended Pixel": 199
      },
      "gdtf": {
        "status": "pending-match",
        "folder": "fixtures/ayrton",
        "suggestedFileName": "Ayrton__Zonda_9_FX.gdtf",
        "file": "fixtures/ayrton/Ayrton@Zonda_9_FX@V1.7_Add_RDM_Personality.gdtf",
        "modes": {
          "Basic": {
            "channels": 26,
            "gdtfMode": "Basic",
            "status": "matched"
          },
          "Standard": {
            "channels": 51,
            "gdtfMode": "",
            "status": "pending-match"
          },
          "Extended Ring": {
            "channels": 54,
            "gdtfMode": "Extended Ring",
            "status": "matched"
          },
          "Extended Pixel": {
            "channels": 199,
            "gdtfMode": "",
            "status": "pending-match"
          }
        }
      },
      "shortName": "Zonda 9 FX"
    },
    {
      "fixture": "Zonda 9 Wash",
      "watts": 1400,
      "weight": 29.2,
      "modes": {
        "Basic": 26,
        "Standard": 51,
        "Extended Ring": 54,
        "Extended Pixel": 199
      },
      "gdtf": {
        "status": "pending-match",
        "folder": "fixtures/ayrton",
        "suggestedFileName": "Ayrton__Zonda_9_Wash.gdtf",
        "file": "fixtures/ayrton/Ayrton@Zonda_9_WASH@V1.7_Add_RDM_Personality.gdtf",
        "modes": {
          "Basic": {
            "channels": 26,
            "gdtfMode": "Basic",
            "status": "matched"
          },
          "Standard": {
            "channels": 51,
            "gdtfMode": "",
            "status": "pending-match"
          },
          "Extended Ring": {
            "channels": 54,
            "gdtfMode": "Extended Ring",
            "status": "matched"
          },
          "Extended Pixel": {
            "channels": 199,
            "gdtfMode": "",
            "status": "pending-match"
          }
        }
      },
      "shortName": "Zonda 9 Wsh"
    }
  ]
}
